email_verify/__init__.py
email_verify/server.py
email_verify_mcp_server-0.1.1.dist-info/METADATA
email_verify_mcp_server-0.1.1.dist-info/WHEEL
email_verify_mcp_server-0.1.1.dist-info/entry_points.txt
email_verify_mcp_server-0.1.1.dist-info/top_level.txt
email_verify_mcp_server-0.1.1.dist-info/RECORD
