Metadata-Version: 2.4
Name: email-verify-mcp-server
Version: 0.1.1
Summary: Add your description here
Requires-Python: >=3.13
Requires-Dist: black>=25.1.0
Requires-Dist: certifi>=2025.1.31
Requires-Dist: dotenv>=0.9.9
Requires-Dist: isort>=6.0.1
Requires-Dist: mcp[cli]>=1.5.0
Requires-Dist: pre-commit>=4.2.0
Requires-Dist: requests>=2.32.3
